procrastimate/cli.py
procrastimate/api/app.py
procrastimate/core/excuses.py
procrastimate/core/models.py
procrastimate/core/scheduler.py
procrastimate/wordList/vagueWords.py
procrastimate/wordList/vaguenessCalculator.py
procrastimate-0.1.1.dist-info/licenses/LICENSE.md
procrastimate-0.1.1.dist-info/METADATA
procrastimate-0.1.1.dist-info/WHEEL
procrastimate-0.1.1.dist-info/entry_points.txt
procrastimate-0.1.1.dist-info/top_level.txt
procrastimate-0.1.1.dist-info/RECORD
