Metadata-Version: 2.4
Name: procrastimate
Version: 0.1.1
Summary: A CLI tool for professional procrastination
Requires-Python: >=3.9
License-File: LICENSE.md
Requires-Dist: fastapi
Requires-Dist: uvicorn
Requires-Dist: pydantic
Requires-Dist: typer
Dynamic: license-file
